{"cameraMode":{"drawMode":0,"name":"Shaded","section":"Shading Mode"},"sceneLighting":false,"audioPlay":false,"sceneViewState":{"showFog":true,"showMaterialUpdate":false,"showSkybox":false,"showFlares":true,"showImageEffects":true,"showParticleSystems":true},"in2DMode":false,"pivot":{"x":1.1229248046875,"y":1.809976577758789,"z":-1.9553626775741578},"rotation":{"x":-0.004027103073894978,"y":-0.9959654808044434,"z":0.05682942643761635,"w":-0.06996016204357147},"size":2.4073948860168459,"orthographic":false}